instaui/__init__.py
instaui/dev.py
instaui/resources.py
instaui/types.py
instaui/version.py
instaui/cdn/__init__.py
instaui/cdn/_cdn.py
instaui/cdn/options.py
instaui/constants/runtime.py
instaui/constants/ui.py
instaui/custom/__init__.py
instaui/custom/_app.py
instaui/custom/_runtime.py
instaui/custom/page_once.py
instaui/debug/api_boundary.py
instaui/debug/config.py
instaui/debug/model.py
instaui/debug/source.py
instaui/debug/source_fallback.py
instaui/experimental/__init__.py
instaui/experimental/debug.py
instaui/facade_ui/__init__.py
instaui/facade_ui/web_launcher.py
instaui/facade_ui/webview_launcher.py
instaui/hooks/__init__.py
instaui/hooks/element_create.py
instaui/internal/import_presets.py
instaui/internal/assets/__init__.py
instaui/internal/assets/base.py
instaui/internal/assets/component_dep.py
instaui/internal/assets/component_extension_registry.py
instaui/internal/assets/context.py
instaui/internal/assets/css_assets.py
instaui/internal/assets/plugin.py
instaui/internal/assets/script_assets.py
instaui/internal/assets/snapshot.py
instaui/internal/assets/style_assets.py
instaui/internal/ast/base.py
instaui/internal/ast/core.py
instaui/internal/ast/expression.py
instaui/internal/ast/h_template.py
instaui/internal/ast/property_key.py
instaui/internal/ast/sfc_template.py
instaui/internal/ast/symbol.py
instaui/internal/ast/symbol_kind.py
instaui/internal/ast/value_rewriter.py
instaui/internal/backend/__init__.py
instaui/internal/backend/base.py
instaui/internal/backend/binding.py
instaui/internal/backend/invocation.py
instaui/internal/backend/common/event_dataset.py
instaui/internal/backend/common/handler.py
instaui/internal/backend/common/python_handler_utils.py
instaui/internal/backend/common/response.py
instaui/internal/backend/fastapi/_utils.py
instaui/internal/backend/fastapi/_uvicorn.py
instaui/internal/backend/fastapi/asset_mapper.py
instaui/internal/backend/fastapi/debug_mode_router.py
instaui/internal/backend/fastapi/dependency_router.py
instaui-0.8.8.dist-info/METADATA
instaui-0.8.8.dist-info/WHEEL
instaui-0.8.8.dist-info/licenses/LICENSE
instaui-0.8.8.dist-info/RECORD
