Metadata-Version: 2.4
Name: instaui
Version: 0.8.8
Summary: insta-ui is a Python-based UI library for rapidly building user interfaces.
Author-email: CrystalWindSnake <568166495@qq.com>
License-Expression: MIT
License-File: LICENSE
Keywords: gui,ui,web
Requires-Python: <3.14,>=3.10
Requires-Dist: jinja2>=3.1.6
Requires-Dist: orjson>=3.10.15
Requires-Dist: pydantic>=2.10.6
Requires-Dist: typing-extensions>=4.13.2
Provides-Extra: all
Requires-Dist: fastapi[standard]; extra == 'all'
Requires-Dist: pywebview; extra == 'all'
Requires-Dist: uvicorn; extra == 'all'
Provides-Extra: web
Requires-Dist: fastapi[standard]; extra == 'web'
Requires-Dist: uvicorn; extra == 'web'
Provides-Extra: webview
Requires-Dist: pywebview; extra == 'webview'
